pylookdata
