Metadata-Version: 2.1
Name: pylookdata
Version: 1.0.2
Summary: Control databases configurations
Home-page: UNKNOWN
Author: Phomint
Author-email: patrick.dev.atom@gmail.com
License: UNKNOWN
Platform: UNKNOWN
